[
  {
    "DAILY GENERATION REPORT - 2025-2026": "SEPC POWER PRIVATE LIMITED\r\n1x525 MW - TTPP Stage IV, Tuticorin - 628004 - TN",
    "__EMPTY_2": "Document Number: SEPC/OPN/S/R - R 00",
    "__EMPTY_15": "count of >12 MU/day",
    "4/1/25": 311,
    "4/1/26": 54,
    "Running Hrs:mm": "Equal Hrs:mm",
    "23735:41": "1900-02-24T00:38:50.000Z",
    "__EMPTY_18": "54 S/D",
    "SN": 1,
    "Particulars": "PAF (TNPDCL A/NA)",
    "UoM": "%",
    "Norms": 80,
    "FY 2021-2022 (Com & COD)": 0,
    "FY 2022-23": 0.8796,
    "FY 2023-24": "86.84 % / 93.96 %",
    "FY 2024-25": "84.37 % / 91.98 %",
    "FY 2025-26 till 05-Feb": "82.07 % 82.07 % "
  },
  {
    "__EMPTY_2": "DAILY",
    "__EMPTY_3": "MTD",
    "__EMPTY_4": "YTD",
    "Running Hrs:mm": "Total Hours:mm",
    "23735:41": "1902-11-10T00:19:50.000Z",
    "SN": 2,
    "Particulars": "PLF",
    "UoM": "%",
    "Norms": "-",
    "FY 2021-2022 (Com & COD)": 0.02363287671232877,
    "FY 2022-23": 0.2006,
    "FY 2023-24": 0.6596,
    "FY 2024-25": 0.661,
    "FY 2025-26 till 05-Feb": 0.6200053785442856
  },
  {
    "__EMPTY": "SN",
    "DAILY GENERATION REPORT - 2025-2026": "PARTICULARS",
    "__EMPTY_1": "Thursday",
    "__EMPTY_2": "2026-02-04T18:29:50.000Z",
    "__EMPTY_3": "February - 2026",
    "__EMPTY_4": "2025-26",
    "186 D(s), 11 H(s), 52 M(s)": 0.013347385582822965,
    "__EMPTY_5": 0.014128829718340395,
    "SN": 3,
    "Particulars": "Power Generation",
    "UoM": "MU",
    "Norms": "-",
    "FY 2021-2022 (Com & COD)": 108.68760000000002,
    "FY 2022-23": 922.437218181818,
    "FY 2023-24": 3041.780127272728,
    "FY 2024-25": 3039.901199999998,
    "FY 2025-26 till 05-Feb": 2429.5530763636366,
    "__EMPTY_30": "SN",
    "__EMPTY_31": "Particulars",
    "__EMPTY_33": "MONTH",
    "__EMPTY_45": "FY 2025-2026"
  },
  {
    "__EMPTY_1": "UoM",
    "__EMPTY_9": "2021 - 2022",
    "__EMPTY_10": "2022-2023",
    "__EMPTY_11": "2023-2024",
    "__EMPTY_12": "2024-2025",
    "SN": 4,
    "Particulars": "Export",
    "UoM": "MU",
    "Norms": "-",
    "FY 2021-2022 (Com & COD)": 99.97090909090909,
    "FY 2022-23": 861.9090909090912,
    "FY 2023-24": 2864.872727272728,
    "FY 2024-25": 2858.1454545454535,
    "FY 2025-26 till 05-Feb": 2295.1781818181803,
    "__EMPTY_31": "Parameters",
    "__EMPTY_32": "UoM",
    "__EMPTY_33": "2025-04-29T18:29:50.000Z",
    "__EMPTY_34": "2025-05-30T18:29:50.000Z",
    "__EMPTY_35": "2025-06-29T18:29:50.000Z",
    "__EMPTY_36": "2025-07-30T18:29:50.000Z",
    "__EMPTY_37": "2025-08-30T18:29:50.000Z",
    "__EMPTY_38": "2025-09-29T18:29:50.000Z",
    "__EMPTY_39": "2025-10-30T18:29:50.000Z",
    "__EMPTY_40": "2025-11-29T18:29:50.000Z",
    "__EMPTY_41": "2025-12-30T18:29:50.000Z",
    "__EMPTY_42": "2026-02-04T18:29:50.000Z",
    "__EMPTY_43": "2026-02-27T18:29:50.000Z",
    "__EMPTY_44": "2026-03-30T18:29:50.000Z",
    "__EMPTY_60": 278.73422
  },
  {
    "__EMPTY": 1,
    "DAILY GENERATION REPORT - 2025-2026": "POWER:",
    "Running Hrs:mm": "Particulars",
    "23735:41": "February - 2026",
    "__EMPTY_18": "FY 2025-26",
    "SN": 5,
    "Particulars": "APC (Excl Import)",
    "UoM": "MU",
    "Norms": "-",
    "FY 2021-2022 (Com & COD)": 8.716690909090929,
    "FY 2022-23": 60.528127272726806,
    "FY 2023-24": 176.9074000000004,
    "FY 2024-25": 181.75574545454447,
    "FY 2025-26 till 05-Feb": 134.3748945454563,
    "__EMPTY_30": 1,
    "__EMPTY_31": "PLF %",
    "__EMPTY_32": "Actual APC",
    "__EMPTY_33": 0.7299646464646472,
    "__EMPTY_34": 0.3970312805474105,
    "__EMPTY_35": 0.2591868686868673,
    "__EMPTY_36": 0,
    "__EMPTY_37": 0.6928963831867053,
    "__EMPTY_38": 0.8061757575757564,
    "__EMPTY_39": 0.8123196480938433,
    "__EMPTY_40": 0.8832313131313113,
    "__EMPTY_41": 0.8693567937438903,
    "__EMPTY_42": 0.6186860606060718,
    "__EMPTY_43": 0.11047965367965569,
    "__EMPTY_44": 0,
    "__EMPTY_45": 0.6200053785442856,
    "__EMPTY_60": 0,
    "__EMPTY_61": "MRM"
  }
]